brenthy_docker/ReadMe.md
brenthy_docker/__init__.py
brenthy_docker/brenthy_docker.py
brenthy_docker-0.3.8.dist-info/METADATA
brenthy_docker-0.3.8.dist-info/WHEEL
brenthy_docker-0.3.8.dist-info/top_level.txt
brenthy_docker-0.3.8.dist-info/RECORD
