Metadata-Version: 2.4
Name: brenthy_docker
Version: 0.3.8
Summary: Interact with docker containers running IPFS and Brenthy.
Project-URL: Github, https://github.com/emendir/BrenthyAndWalytis/tree/master/tests/brenthy_docker/brenthy_docker/ReadMe.md
Project-URL: Homepage, https://ipfs.io/ipns/emendir.tech/#BrenthyAndWalytis/tests/brenthy_docker/brenthy_docker/ReadMe.md
Project-URL: IPNS, https://ipfs.io/ipns/emendir.tech/#BrenthyAndWalytis/tests/brenthy_docker/brenthy_docker/ReadMe.md
Keywords: brenthy,walytis,docker,test
Requires-Dist: docker
Requires-Dist: ipfs-toolkit
Requires-Dist: termcolor
Requires-Dist: pyperclip
Requires-Dist: pexpect
Requires-Dist: walytis_beta_api
